gtauthclient/__init__.py
gtauthclient-0.0.7.dist-info/LICENSE
gtauthclient-0.0.7.dist-info/METADATA
gtauthclient-0.0.7.dist-info/WHEEL
gtauthclient-0.0.7.dist-info/top_level.txt
gtauthclient-0.0.7.dist-info/RECORD
