Metadata-Version: 2.1
Name: gtauthclient
Version: 0.0.7
Summary: GT Auth Client Functions
Author: Josh XT
Author-email: josh@devxt.com
Requires-Python: >=3.10
License-File: LICENSE
Requires-Dist: fastapi
Requires-Dist: PyJWT
Requires-Dist: pycryptodome
